{"nodes": [{"id": "d_git_newpdfding_pdfding_admin_views_py", "label": "views.py", "file_type": "code", "source_file": "pdfding/admin/views.py", "source_location": "L1"}, {"id": "admin_views_baseadminrequiredmixin", "label": "BaseAdminRequiredMixin", "file_type": "code", "source_file": "pdfding/admin/views.py", "source_location": "L14"}, {"id": "userpassestestmixin", "label": "UserPassesTestMixin", "file_type": "code", "source_file": "", "source_location": ""}, {"id": "admin_views_baseadminrequiredmixin_test_func", "label": ".test_func()", "file_type": "code", "source_file": "pdfding/admin/views.py", "source_location": "L15"}, {"id": "admin_views_baseadminmixin", "label": "BaseAdminMixin", "file_type": "code", "source_file": "pdfding/admin/views.py", "source_location": "L22"}, {"id": "admin_views_overviewmixin", "label": "OverviewMixin", "file_type": "code", "source_file": "pdfding/admin/views.py", "source_location": "L26"}, {"id": "admin_views_overviewmixin_get_sorting", "label": ".get_sorting()", "file_type": "code", "source_file": "pdfding/admin/views.py", "source_location": "L30"}, {"id": "httprequest", "label": "HttpRequest", "file_type": "code", "source_file": "", "source_location": ""}, {"id": "admin_views_overviewmixin_filter_objects", "label": ".filter_objects()", "file_type": "code", "source_file": "pdfding/admin/views.py", "source_location": "L45"}, {"id": "queryset", "label": "QuerySet", "file_type": "code", "source_file": "", "source_location": ""}, {"id": "admin_views_overviewmixin_get_extra_context", "label": ".get_extra_context()", "file_type": "code", "source_file": "pdfding/admin/views.py", "source_location": "L66"}, {"id": "admin_views_adminmixin", "label": "AdminMixin", "file_type": "code", "source_file": "pdfding/admin/views.py", "source_location": "L82"}, {"id": "admin_views_adminmixin_get_object", "label": ".get_object()", "file_type": "code", "source_file": "pdfding/admin/views.py", "source_location": "L84"}, {"id": "admin_views_overview", "label": "Overview", "file_type": "code", "source_file": "pdfding/admin/views.py", "source_location": "L90"}, {"id": "admin_views_overviewquery", "label": "OverviewQuery", "file_type": "code", "source_file": "pdfding/admin/views.py", "source_location": "L97"}, {"id": "admin_views_deleteprofile", "label": "DeleteProfile", "file_type": "code", "source_file": "pdfding/admin/views.py", "source_location": "L103"}, {"id": "admin_views_adjustadminrights", "label": "AdjustAdminRights", "file_type": "code", "source_file": "pdfding/admin/views.py", "source_location": "L107"}, {"id": "view", "label": "View", "file_type": "code", "source_file": "", "source_location": ""}, {"id": "admin_views_adjustadminrights_post", "label": ".post()", "file_type": "code", "source_file": "pdfding/admin/views.py", "source_location": "L110"}, {"id": "admin_views_information", "label": "Information", "file_type": "code", "source_file": "pdfding/admin/views.py", "source_location": "L130"}, {"id": "admin_views_information_get", "label": ".get()", "file_type": "code", "source_file": "pdfding/admin/views.py", "source_location": "L133"}, {"id": "admin_views_rationale_31", "label": "Get the sorting of the overview page.", "file_type": "rationale", "source_file": "pdfding/admin/views.py", "source_location": "L31"}, {"id": "admin_views_rationale_46", "label": "Filter the PDFs when performing a search in the overview.", "file_type": "rationale", "source_file": "pdfding/admin/views.py", "source_location": "L46"}, {"id": "admin_views_rationale_67", "label": "get further information that needs to be passed to the template.", "file_type": "rationale", "source_file": "pdfding/admin/views.py", "source_location": "L67"}, {"id": "admin_views_rationale_91", "label": "View for the user overview page. This view performs the searching and sorting of", "file_type": "rationale", "source_file": "pdfding/admin/views.py", "source_location": "L91"}, {"id": "admin_views_rationale_98", "label": "View for performing searches and sorting on the user overview page.", "file_type": "rationale", "source_file": "pdfding/admin/views.py", "source_location": "L98"}, {"id": "admin_views_rationale_104", "label": "View for deleting a user profile", "file_type": "rationale", "source_file": "pdfding/admin/views.py", "source_location": "L104"}, {"id": "admin_views_rationale_108", "label": "View for adjusting the admin rights", "file_type": "rationale", "source_file": "pdfding/admin/views.py", "source_location": "L108"}, {"id": "admin_views_rationale_131", "label": "View for getting instance information", "file_type": "rationale", "source_file": "pdfding/admin/views.py", "source_location": "L131"}, {"id": "admin_views_rationale_134", "label": "Get instance information", "file_type": "rationale", "source_file": "pdfding/admin/views.py", "source_location": "L134"}], "edges": [{"source": "d_git_newpdfding_pdfding_admin_views_py", "target": "base", "relation": "imports_from", "context": "import", "confidence": "EXTRACTED", "source_file": "pdfding/admin/views.py", "source_location": "L1", "weight": 1.0}, {"source": "d_git_newpdfding_pdfding_admin_views_py", "target": "django_conf", "relation": "imports_from", "context": "import", "confidence": "EXTRACTED", "source_file": "pdfding/admin/views.py", "source_location": "L2", "weight": 1.0}, {"source": "d_git_newpdfding_pdfding_admin_views_py", "target": "django_contrib_auth_mixins", "relation": "imports_from", "context": "import", "confidence": "EXTRACTED", "source_file": "pdfding/admin/views.py", "source_location": "L3", "weight": 1.0}, {"source": "d_git_newpdfding_pdfding_admin_views_py", "target": "django_contrib_auth_models", "relation": "imports_from", "context": "import", "confidence": "EXTRACTED", "source_file": "pdfding/admin/views.py", "source_location": "L4", "weight": 1.0}, {"source": "d_git_newpdfding_pdfding_admin_views_py", "target": "django_db_models", "relation": "imports_from", "context": "import", "confidence": "EXTRACTED", "source_file": "pdfding/admin/views.py", "source_location": "L5", "weight": 1.0}, {"source": "d_git_newpdfding_pdfding_admin_views_py", "target": "django_db_models_functions", "relation": "imports_from", "context": "import", "confidence": "EXTRACTED", "source_file": "pdfding/admin/views.py", "source_location": "L6", "weight": 1.0}, {"source": "d_git_newpdfding_pdfding_admin_views_py", "target": "django_http", "relation": "imports_from", "context": "import", "confidence": "EXTRACTED", "source_file": "pdfding/admin/views.py", "source_location": "L7", "weight": 1.0}, {"source": "d_git_newpdfding_pdfding_admin_views_py", "target": "django_shortcuts", "relation": "imports_from", "context": "import", "confidence": "EXTRACTED", "source_file": "pdfding/admin/views.py", "source_location": "L8", "weight": 1.0}, {"source": "d_git_newpdfding_pdfding_admin_views_py", "target": "django_views", "relation": "imports_from", "context": "import", "confidence": "EXTRACTED", "source_file": "pdfding/admin/views.py", "source_location": "L9", "weight": 1.0}, {"source": "d_git_newpdfding_pdfding_admin_views_py", "target": "django_htmx_http", "relation": "imports_from", "context": "import", "confidence": "EXTRACTED", "source_file": "pdfding/admin/views.py", "source_location": "L10", "weight": 1.0}, {"source": "d_git_newpdfding_pdfding_admin_views_py", "target": "pdf_models_pdf_models", "relation": "imports_from", "context": "import", "confidence": "EXTRACTED", "source_file": "pdfding/admin/views.py", "source_location": "L11", "weight": 1.0}, {"source": "d_git_newpdfding_pdfding_admin_views_py", "target": "admin_views_baseadminrequiredmixin", "relation": "contains", "confidence": "EXTRACTED", "source_file": "pdfding/admin/views.py", "source_location": "L14", "weight": 1.0}, {"source": "admin_views_baseadminrequiredmixin", "target": "userpassestestmixin", "relation": "inherits", "confidence": "EXTRACTED", "source_file": "pdfding/admin/views.py", "source_location": "L14", "weight": 1.0}, {"source": "admin_views_baseadminrequiredmixin", "target": "admin_views_baseadminrequiredmixin_test_func", "relation": "method", "confidence": "EXTRACTED", "source_file": "pdfding/admin/views.py", "source_location": "L15", "weight": 1.0}, {"source": "d_git_newpdfding_pdfding_admin_views_py", "target": "admin_views_baseadminmixin", "relation": "contains", "confidence": "EXTRACTED", "source_file": "pdfding/admin/views.py", "source_location": "L22", "weight": 1.0}, {"source": "d_git_newpdfding_pdfding_admin_views_py", "target": "admin_views_overviewmixin", "relation": "contains", "confidence": "EXTRACTED", "source_file": "pdfding/admin/views.py", "source_location": "L26", "weight": 1.0}, {"source": "admin_views_overviewmixin", "target": "admin_views_baseadminmixin", "relation": "inherits", "confidence": "EXTRACTED", "source_file": "pdfding/admin/views.py", "source_location": "L26", "weight": 1.0}, {"source": "admin_views_overviewmixin", "target": "admin_views_overviewmixin_get_sorting", "relation": "method", "confidence": "EXTRACTED", "source_file": "pdfding/admin/views.py", "source_location": "L30", "weight": 1.0}, {"source": "admin_views_overviewmixin_get_sorting", "target": "httprequest", "relation": "references", "context": "parameter_type", "confidence": "EXTRACTED", "source_file": "pdfding/admin/views.py", "source_location": "L30", "weight": 1.0}, {"source": "admin_views_overviewmixin", "target": "admin_views_overviewmixin_filter_objects", "relation": "method", "confidence": "EXTRACTED", "source_file": "pdfding/admin/views.py", "source_location": "L45", "weight": 1.0}, {"source": "admin_views_overviewmixin_filter_objects", "target": "httprequest", "relation": "references", "context": "parameter_type", "confidence": "EXTRACTED", "source_file": "pdfding/admin/views.py", "source_location": "L45", "weight": 1.0}, {"source": "admin_views_overviewmixin_filter_objects", "target": "queryset", "relation": "references", "context": "return_type", "confidence": "EXTRACTED", "source_file": "pdfding/admin/views.py", "source_location": "L45", "weight": 1.0}, {"source": "admin_views_overviewmixin", "target": "admin_views_overviewmixin_get_extra_context", "relation": "method", "confidence": "EXTRACTED", "source_file": "pdfding/admin/views.py", "source_location": "L66", "weight": 1.0}, {"source": "admin_views_overviewmixin_get_extra_context", "target": "httprequest", "relation": "references", "context": "parameter_type", "confidence": "EXTRACTED", "source_file": "pdfding/admin/views.py", "source_location": "L66", "weight": 1.0}, {"source": "d_git_newpdfding_pdfding_admin_views_py", "target": "admin_views_adminmixin", "relation": "contains", "confidence": "EXTRACTED", "source_file": "pdfding/admin/views.py", "source_location": "L82", "weight": 1.0}, {"source": "admin_views_adminmixin", "target": "admin_views_baseadminmixin", "relation": "inherits", "confidence": "EXTRACTED", "source_file": "pdfding/admin/views.py", "source_location": "L82", "weight": 1.0}, {"source": "admin_views_adminmixin", "target": "admin_views_adminmixin_get_object", "relation": "method", "confidence": "EXTRACTED", "source_file": "pdfding/admin/views.py", "source_location": "L84", "weight": 1.0}, {"source": "d_git_newpdfding_pdfding_admin_views_py", "target": "admin_views_overview", "relation": "contains", "confidence": "EXTRACTED", "source_file": "pdfding/admin/views.py", "source_location": "L90", "weight": 1.0}, {"source": "admin_views_overview", "target": "admin_views_baseadminrequiredmixin", "relation": "inherits", "confidence": "EXTRACTED", "source_file": "pdfding/admin/views.py", "source_location": "L90", "weight": 1.0}, {"source": "admin_views_overview", "target": "admin_views_overviewmixin", "relation": "inherits", "confidence": "EXTRACTED", "source_file": "pdfding/admin/views.py", "source_location": "L90", "weight": 1.0}, {"source": "d_git_newpdfding_pdfding_admin_views_py", "target": "admin_views_overviewquery", "relation": "contains", "confidence": "EXTRACTED", "source_file": "pdfding/admin/views.py", "source_location": "L97", "weight": 1.0}, {"source": "d_git_newpdfding_pdfding_admin_views_py", "target": "admin_views_deleteprofile", "relation": "contains", "confidence": "EXTRACTED", "source_file": "pdfding/admin/views.py", "source_location": "L103", "weight": 1.0}, {"source": "admin_views_deleteprofile", "target": "admin_views_baseadminrequiredmixin", "relation": "inherits", "confidence": "EXTRACTED", "source_file": "pdfding/admin/views.py", "source_location": "L103", "weight": 1.0}, {"source": "admin_views_deleteprofile", "target": "admin_views_adminmixin", "relation": "inherits", "confidence": "EXTRACTED", "source_file": "pdfding/admin/views.py", "source_location": "L103", "weight": 1.0}, {"source": "d_git_newpdfding_pdfding_admin_views_py", "target": "admin_views_adjustadminrights", "relation": "contains", "confidence": "EXTRACTED", "source_file": "pdfding/admin/views.py", "source_location": "L107", "weight": 1.0}, {"source": "admin_views_adjustadminrights", "target": "admin_views_baseadminrequiredmixin", "relation": "inherits", "confidence": "EXTRACTED", "source_file": "pdfding/admin/views.py", "source_location": "L107", "weight": 1.0}, {"source": "admin_views_adjustadminrights", "target": "view", "relation": "inherits", "confidence": "EXTRACTED", "source_file": "pdfding/admin/views.py", "source_location": "L107", "weight": 1.0}, {"source": "admin_views_adjustadminrights", "target": "admin_views_adjustadminrights_post", "relation": "method", "confidence": "EXTRACTED", "source_file": "pdfding/admin/views.py", "source_location": "L110", "weight": 1.0}, {"source": "admin_views_adjustadminrights_post", "target": "httprequest", "relation": "references", "context": "parameter_type", "confidence": "EXTRACTED", "source_file": "pdfding/admin/views.py", "source_location": "L110", "weight": 1.0}, {"source": "d_git_newpdfding_pdfding_admin_views_py", "target": "admin_views_information", "relation": "contains", "confidence": "EXTRACTED", "source_file": "pdfding/admin/views.py", "source_location": "L130", "weight": 1.0}, {"source": "admin_views_information", "target": "view", "relation": "inherits", "confidence": "EXTRACTED", "source_file": "pdfding/admin/views.py", "source_location": "L130", "weight": 1.0}, {"source": "admin_views_information", "target": "admin_views_information_get", "relation": "method", "confidence": "EXTRACTED", "source_file": "pdfding/admin/views.py", "source_location": "L133", "weight": 1.0}, {"source": "admin_views_information_get", "target": "httprequest", "relation": "references", "context": "parameter_type", "confidence": "EXTRACTED", "source_file": "pdfding/admin/views.py", "source_location": "L133", "weight": 1.0}, {"source": "admin_views_overviewmixin_filter_objects", "target": "admin_views_information_get", "relation": "calls", "context": "call", "confidence": "EXTRACTED", "source_file": "pdfding/admin/views.py", "source_location": "L52", "weight": 1.0}, {"source": "admin_views_overviewmixin_get_extra_context", "target": "admin_views_information_get", "relation": "calls", "context": "call", "confidence": "EXTRACTED", "source_file": "pdfding/admin/views.py", "source_location": "L69", "weight": 1.0}, {"source": "admin_views_adminmixin_get_object", "target": "admin_views_information_get", "relation": "calls", "context": "call", "confidence": "EXTRACTED", "source_file": "pdfding/admin/views.py", "source_location": "L85", "weight": 1.0}, {"source": "admin_views_adjustadminrights_post", "target": "admin_views_information_get", "relation": "calls", "context": "call", "confidence": "EXTRACTED", "source_file": "pdfding/admin/views.py", "source_location": "L114", "weight": 1.0}, {"source": "admin_views_rationale_31", "target": "admin_views_overviewmixin_get_sorting", "relation": "rationale_for", "confidence": "EXTRACTED", "source_file": "pdfding/admin/views.py", "source_location": "L31", "weight": 1.0}, {"source": "admin_views_rationale_46", "target": "admin_views_overviewmixin_filter_objects", "relation": "rationale_for", "confidence": "EXTRACTED", "source_file": "pdfding/admin/views.py", "source_location": "L46", "weight": 1.0}, {"source": "admin_views_rationale_67", "target": "admin_views_overviewmixin_get_extra_context", "relation": "rationale_for", "confidence": "EXTRACTED", "source_file": "pdfding/admin/views.py", "source_location": "L67", "weight": 1.0}, {"source": "admin_views_rationale_91", "target": "admin_views_overview", "relation": "rationale_for", "confidence": "EXTRACTED", "source_file": "pdfding/admin/views.py", "source_location": "L91", "weight": 1.0}, {"source": "admin_views_rationale_98", "target": "admin_views_overviewquery", "relation": "rationale_for", "confidence": "EXTRACTED", "source_file": "pdfding/admin/views.py", "source_location": "L98", "weight": 1.0}, {"source": "admin_views_rationale_104", "target": "admin_views_deleteprofile", "relation": "rationale_for", "confidence": "EXTRACTED", "source_file": "pdfding/admin/views.py", "source_location": "L104", "weight": 1.0}, {"source": "admin_views_rationale_108", "target": "admin_views_adjustadminrights", "relation": "rationale_for", "confidence": "EXTRACTED", "source_file": "pdfding/admin/views.py", "source_location": "L108", "weight": 1.0}, {"source": "admin_views_rationale_131", "target": "admin_views_information", "relation": "rationale_for", "confidence": "EXTRACTED", "source_file": "pdfding/admin/views.py", "source_location": "L131", "weight": 1.0}, {"source": "admin_views_rationale_134", "target": "admin_views_information_get", "relation": "rationale_for", "confidence": "EXTRACTED", "source_file": "pdfding/admin/views.py", "source_location": "L134", "weight": 1.0}], "raw_calls": [{"caller_nid": "admin_views_baseadminrequiredmixin_test_func", "callee": "Http404", "is_member_call": false, "source_file": "D:\\git\\newPdfDing\\pdfding\\admin\\views.py", "source_location": "L19", "receiver": null}, {"caller_nid": "admin_views_overviewmixin_get_sorting", "callee": "Lower", "is_member_call": false, "source_file": "D:\\git\\newPdfDing\\pdfding\\admin\\views.py", "source_location": "L38", "receiver": null}, {"caller_nid": "admin_views_overviewmixin_get_sorting", "callee": "desc", "is_member_call": true, "source_file": "D:\\git\\newPdfDing\\pdfding\\admin\\views.py", "source_location": "L39", "receiver": null}, {"caller_nid": "admin_views_overviewmixin_get_sorting", "callee": "Lower", "is_member_call": false, "source_file": "D:\\git\\newPdfDing\\pdfding\\admin\\views.py", "source_location": "L39", "receiver": null}, {"caller_nid": "admin_views_overviewmixin_filter_objects", "callee": "split", "is_member_call": true, "source_file": "D:\\git\\newPdfDing\\pdfding\\admin\\views.py", "source_location": "L55", "receiver": null}, {"caller_nid": "admin_views_overviewmixin_get_extra_context", "callee": "split", "is_member_call": true, "source_file": "D:\\git\\newPdfDing\\pdfding\\admin\\views.py", "source_location": "L71", "receiver": null}, {"caller_nid": "admin_views_adjustadminrights_post", "callee": "save", "is_member_call": true, "source_file": "D:\\git\\newPdfDing\\pdfding\\admin\\views.py", "source_location": "L123", "receiver": null}, {"caller_nid": "admin_views_adjustadminrights_post", "callee": "HttpResponseClientRefresh", "is_member_call": false, "source_file": "D:\\git\\newPdfDing\\pdfding\\admin\\views.py", "source_location": "L125", "receiver": null}, {"caller_nid": "admin_views_adjustadminrights_post", "callee": "redirect", "is_member_call": false, "source_file": "D:\\git\\newPdfDing\\pdfding\\admin\\views.py", "source_location": "L127", "receiver": null}, {"caller_nid": "admin_views_information_get", "callee": "count", "is_member_call": true, "source_file": "D:\\git\\newPdfDing\\pdfding\\admin\\views.py", "source_location": "L136", "receiver": null}, {"caller_nid": "admin_views_information_get", "callee": "count", "is_member_call": true, "source_file": "D:\\git\\newPdfDing\\pdfding\\admin\\views.py", "source_location": "L137", "receiver": null}, {"caller_nid": "admin_views_information_get", "callee": "render", "is_member_call": false, "source_file": "D:\\git\\newPdfDing\\pdfding\\admin\\views.py", "source_location": "L145", "receiver": null}]}